memodocs-1.1.0.dist-info/METADATA
memodocs-1.1.0.dist-info/WHEEL
memodocs-1.1.0.dist-info/licenses/LICENSE
memodocs/__init__.py
memodocs/memodocs.cp310-win_amd64.pyd
memodocs-1.1.0.dist-info/RECORD
